{"1974":{"crse_id":"000120","subject":"ASMT","catalog_nbr":"431","course_title_long":"US Histories","descrlong":"","units_minimum":"1","units_maximum":"1","crse_offer_nbr":"1","term":"1974","crse_attr_list":"CSLI=N, ULR=UUSH"},"1981":{"crse_id":"000120","subject":"ASMT","catalog_nbr":"431","course_title_long":"US Histories","descrlong":"","units_minimum":"1","units_maximum":"1","crse_offer_nbr":"1","term":"1981","crse_attr_list":"CSLI=N, ULR=UUSH"},"1982":{"crse_id":"000120","subject":"ASMT","catalog_nbr":"431","course_title_long":"US Histories","descrlong":"","units_minimum":"1","units_maximum":"1","crse_offer_nbr":"1","term":"1982","crse_attr_list":"CSLI=N, ULR=UUSH"},"1983":{"crse_id":"000120","subject":"ASMT","catalog_nbr":"431","course_title_long":"US Histories","descrlong":"","units_minimum":"1","units_maximum":"1","crse_offer_nbr":"1","term":"1983","crse_attr_list":"CSLI=N, ULR=UUSH"},"1984":{"crse_id":"000120","subject":"ASMT","catalog_nbr":"431","course_title_long":"US Histories","descrlong":"","units_minimum":"1","units_maximum":"1","crse_offer_nbr":"1","term":"1984","crse_attr_list":"CSLI=N, ULR=UUSH"},"1991":{"crse_id":"000120","subject":"ASMT","catalog_nbr":"431","course_title_long":"US Histories","descrlong":"","units_minimum":"1","units_maximum":"1","crse_offer_nbr":"1","term":"1991","crse_attr_list":"CSLI=N, ULR=UUSH"},"1992":{"crse_id":"000120","subject":"ASMT","catalog_nbr":"431","course_title_long":"US Histories","descrlong":"","units_minimum":"1","units_maximum":"1","crse_offer_nbr":"1","term":"1992","crse_attr_list":"CSLI=N, ULR=UUSH"},"1993":{"crse_id":"000120","subject":"ASMT","catalog_nbr":"431","course_title_long":"US Histories","descrlong":"","units_minimum":"1","units_maximum":"1","crse_offer_nbr":"1","term":"1993","crse_attr_list":"CSLI=N, ULR=UUSH"},"1994":{"crse_id":"000120","subject":"ASMT","catalog_nbr":"431","course_title_long":"US Histories","descrlong":"","units_minimum":"1","units_maximum":"1","crse_offer_nbr":"1","term":"1994","crse_attr_list":"CSLI=N, ULR=UUSH"},"2001":{"crse_id":"000120","subject":"ASMT","catalog_nbr":"431","course_title_long":"US Histories","descrlong":"","units_minimum":"1","units_maximum":"1","crse_offer_nbr":"1","term":"2001","crse_attr_list":"CSLI=N, ULR=UUSH"},"2002":{"crse_id":"000120","subject":"ASMT","catalog_nbr":"431","course_title_long":"US Histories","descrlong":"","units_minimum":"1","units_maximum":"1","crse_offer_nbr":"1","term":"2002","crse_attr_list":"CSLI=N, ULR=UUSH"},"2003":{"crse_id":"000120","subject":"ASMT","catalog_nbr":"431","course_title_long":"US Histories","descrlong":"","units_minimum":"1","units_maximum":"1","crse_offer_nbr":"1","term":"2003","crse_attr_list":"CSLI=N, ULR=UUSH"},"2004":{"crse_id":"000120","subject":"ASMT","catalog_nbr":"431","course_title_long":"US Histories","descrlong":"","units_minimum":"1","units_maximum":"1","crse_offer_nbr":"1","term":"2004","crse_attr_list":"CSLI=N, ULR=UUSH"},"2011":{"crse_id":"000120","subject":"ASMT","catalog_nbr":"431","course_title_long":"US Histories","descrlong":"","units_minimum":"1","units_maximum":"1","crse_offer_nbr":"1","term":"2011","crse_attr_list":"CSLI=N, ULR=UUSH"},"2012":{"crse_id":"000120","subject":"ASMT","catalog_nbr":"431","course_title_long":"US Histories","descrlong":"","units_minimum":"1","units_maximum":"1","crse_offer_nbr":"1","term":"2012","crse_attr_list":"CSLI=N, ULR=UUSH"},"2013":{"crse_id":"000120","subject":"ASMT","catalog_nbr":"431","course_title_long":"US Histories","descrlong":"","units_minimum":"1","units_maximum":"1","crse_offer_nbr":"1","term":"2013","crse_attr_list":"CSLI=N, ULR=UUSH"},"2014":{"crse_id":"000120","subject":"ASMT","catalog_nbr":"431","course_title_long":"US Histories","descrlong":"","units_minimum":"1","units_maximum":"1","crse_offer_nbr":"1","term":"2014","crse_attr_list":"CSLI=N, ULR=UUSH"},"2021":{"crse_id":"000120","subject":"ASMT","catalog_nbr":"431","course_title_long":"US Histories","descrlong":"","units_minimum":"1","units_maximum":"1","crse_offer_nbr":"1","term":"2021","crse_attr_list":"CSLI=N, ULR=UUSH"},"2022":{"crse_id":"000120","subject":"ASMT","catalog_nbr":"431","course_title_long":"US Histories","descrlong":"","units_minimum":"1","units_maximum":"1","crse_offer_nbr":"1","term":"2022","crse_attr_list":"CSLI=N, ULR=UUSH"},"2023":{"crse_id":"000120","subject":"ASMT","catalog_nbr":"431","course_title_long":"US Histories","descrlong":"","units_minimum":"1","units_maximum":"1","crse_offer_nbr":"1","term":"2023","crse_attr_list":"CSLI=N, ULR=UUSH"},"2024":{"crse_id":"000120","subject":"ASMT","catalog_nbr":"431","course_title_long":"US Histories","descrlong":"","units_minimum":"1","units_maximum":"1","crse_offer_nbr":"1","term":"2024","crse_attr_list":"CSLI=N, ULR=UUSH"},"2031":{"crse_id":"000120","subject":"ASMT","catalog_nbr":"431","course_title_long":"US Histories","descrlong":"","units_minimum":"1","units_maximum":"1","crse_offer_nbr":"1","term":"2031","crse_attr_list":"CSLI=N, ULR=UUSH"},"2032":{"crse_id":"000120","subject":"ASMT","catalog_nbr":"431","course_title_long":"US Histories","descrlong":"","units_minimum":"1","units_maximum":"1","crse_offer_nbr":"1","term":"2032","crse_attr_list":"CSLI=N, ULR=UUSH"},"2033":{"crse_id":"000120","subject":"ASMT","catalog_nbr":"431","course_title_long":"US Histories","descrlong":"","units_minimum":"1","units_maximum":"1","crse_offer_nbr":"1","term":"2033","crse_attr_list":"CSLI=N, ULR=UUSH"},"2034":{"crse_id":"000120","subject":"ASMT","catalog_nbr":"431","course_title_long":"US Histories","descrlong":"","units_minimum":"1","units_maximum":"1","crse_offer_nbr":"1","term":"2034","crse_attr_list":"CSLI=N, ULR=UUSH"},"2041":{"crse_id":"000120","subject":"ASMT","catalog_nbr":"431","course_title_long":"US Histories","descrlong":"","units_minimum":"1","units_maximum":"1","crse_offer_nbr":"1","term":"2041","crse_attr_list":"CSLI=N, ULR=UUSH"},"2042":{"crse_id":"000120","subject":"ASMT","catalog_nbr":"431","course_title_long":"US Histories","descrlong":"","units_minimum":"1","units_maximum":"1","crse_offer_nbr":"1","term":"2042","crse_attr_list":"CSLI=N, ULR=UUSH"},"2043":{"crse_id":"000120","subject":"ASMT","catalog_nbr":"431","course_title_long":"US Histories","descrlong":"","units_minimum":"1","units_maximum":"1","crse_offer_nbr":"1","term":"2043","crse_attr_list":"CSLI=N, ULR=UUSH"},"2044":{"crse_id":"000120","subject":"ASMT","catalog_nbr":"431","course_title_long":"US Histories","descrlong":"","units_minimum":"1","units_maximum":"1","crse_offer_nbr":"1","term":"2044","crse_attr_list":"CSLI=N, ULR=UUSH"},"2051":{"crse_id":"000120","subject":"ASMT","catalog_nbr":"431","course_title_long":"US Histories","descrlong":"","units_minimum":"1","units_maximum":"1","crse_offer_nbr":"1","term":"2051","crse_attr_list":"CSLI=N, ULR=UUSH"},"2052":{"crse_id":"000120","subject":"ASMT","catalog_nbr":"431","course_title_long":"US Histories","descrlong":"Alternative assessment of the U.S. Histories (HIST) University Learning Requirement.","units_minimum":"1","units_maximum":"1","crse_offer_nbr":"1","term":"2052","crse_attr_list":"CSLI=N, ULR=UUSH"},"2053":{"crse_id":"000120","subject":"ASMT","catalog_nbr":"431","course_title_long":"US Histories","descrlong":"Alternative assessment of the U.S. Histories (HIST) University Learning Requirement.","units_minimum":"1","units_maximum":"1","crse_offer_nbr":"1","term":"2053","crse_attr_list":"CSLI=N, ULR=UUSH"},"2054":{"crse_id":"000120","subject":"ASMT","catalog_nbr":"431","course_title_long":"US Histories","descrlong":"Alternative assessment of the U.S. Histories (HIST) University Learning Requirement.","units_minimum":"1","units_maximum":"1","crse_offer_nbr":"1","term":"2054","crse_attr_list":"CSLI=N, ULR=UUSH"},"2061":{"crse_id":"000120","subject":"ASMT","catalog_nbr":"431","course_title_long":"US Histories","descrlong":"Alternative assessment of the U.S. Histories (HIST) University Learning Requirement.","units_minimum":"1","units_maximum":"1","crse_offer_nbr":"1","term":"2061","crse_attr_list":"CSLI=N, ULR=UUSH"},"2062":{"crse_id":"000120","subject":"ASMT","catalog_nbr":"431","course_title_long":"US Histories","descrlong":"Alternative assessment of the U.S. Histories (HIST) University Learning Requirement.","units_minimum":"1","units_maximum":"1","crse_offer_nbr":"1","term":"2062","crse_attr_list":"CSLI=N, ULR=UUSH"},"2063":{"crse_id":"000120","subject":"ASMT","catalog_nbr":"431","course_title_long":"US Histories","descrlong":"Alternative assessment of the U.S. Histories (HIST) University Learning Requirement.","units_minimum":"1","units_maximum":"1","crse_offer_nbr":"1","term":"2063","crse_attr_list":"CSLI=N, ULR=UUSH"},"2064":{"crse_id":"000120","subject":"ASMT","catalog_nbr":"431","course_title_long":"US Histories","descrlong":"Alternative assessment of the U.S. Histories (HIST) University Learning Requirement.","units_minimum":"1","units_maximum":"1","crse_offer_nbr":"1","term":"2064","crse_attr_list":"CSLI=N, ULR=UUSH"},"2071":{"crse_id":"000120","subject":"ASMT","catalog_nbr":"431","course_title_long":"US Histories","descrlong":"Alternative assessment of the U.S. Histories (HIST) University Learning Requirement.","units_minimum":"1","units_maximum":"1","crse_offer_nbr":"1","term":"2071","crse_attr_list":"CSLI=N, ULR=UUSH"},"2072":{"crse_id":"000120","subject":"ASMT","catalog_nbr":"431","course_title_long":"US Histories","descrlong":"Alternative assessment of the U.S. Histories (HIST) University Learning Requirement.","units_minimum":"1","units_maximum":"1","crse_offer_nbr":"1","term":"2072","crse_attr_list":"CSLI=N, ULR=UUSH"},"2073":{"crse_id":"000120","subject":"ASMT","catalog_nbr":"431","course_title_long":"US Histories","descrlong":"Alternative assessment of the U.S. Histories (HIST) University Learning Requirement.","units_minimum":"1","units_maximum":"1","crse_offer_nbr":"1","term":"2073","crse_attr_list":"CSLI=N, ULR=UUSH"},"2074":{"crse_id":"000120","subject":"ASMT","catalog_nbr":"431","course_title_long":"US Histories","descrlong":"Alternative assessment of the U.S. Histories (HIST) University Learning Requirement.","units_minimum":"1","units_maximum":"1","crse_offer_nbr":"1","term":"2074","crse_attr_list":"CSLI=N, ULR=UUSH"},"2081":{"crse_id":"000120","subject":"ASMT","catalog_nbr":"431","course_title_long":"US Histories","descrlong":"Alternative assessment of the U.S. Histories (HIST) University Learning Requirement.","units_minimum":"1","units_maximum":"1","crse_offer_nbr":"1","term":"2081","crse_attr_list":"CSLI=N, ULR=UUSH"},"2082":{"crse_id":"000120","subject":"ASMT","catalog_nbr":"431","course_title_long":"US Histories","descrlong":"Alternative assessment of the U.S. Histories (HIST) University Learning Requirement.","units_minimum":"1","units_maximum":"1","crse_offer_nbr":"1","term":"2082","crse_attr_list":"CSLI=N, ULR=UUSH"},"2083":{"crse_id":"000120","subject":"ASMT","catalog_nbr":"431","course_title_long":"US Histories","descrlong":"Alternative assessment of the U.S. Histories (HIST) University Learning Requirement.","units_minimum":"1","units_maximum":"1","crse_offer_nbr":"1","term":"2083","crse_attr_list":"CSLI=N, ULR=UUSH"},"2084":{"crse_id":"000120","subject":"ASMT","catalog_nbr":"431","course_title_long":"US Histories","descrlong":"Alternative assessment of the U.S. Histories (HIST) University Learning Requirement.","units_minimum":"1","units_maximum":"1","crse_offer_nbr":"1","term":"2084","crse_attr_list":"CSLI=N, ULR=UUSH"},"2091":{"crse_id":"000120","subject":"ASMT","catalog_nbr":"431","course_title_long":"US Histories","descrlong":"Alternative assessment of the U.S. Histories (HIST) University Learning Requirement.","units_minimum":"1","units_maximum":"1","crse_offer_nbr":"1","term":"2091","crse_attr_list":"CSLI=N, ULR=UUSH"},"2092":{"crse_id":"000120","subject":"ASMT","catalog_nbr":"431","course_title_long":"US Histories","descrlong":"Alternative assessment of the U.S. Histories (HIST) University Learning Requirement.","units_minimum":"1","units_maximum":"1","crse_offer_nbr":"1","term":"2092","crse_attr_list":"CSLI=N, ULR=UUSH"},"2093":{"crse_id":"000120","subject":"ASMT","catalog_nbr":"431","course_title_long":"US Histories","descrlong":"Alternative assessment of the U.S. Histories (HIST) University Learning Requirement.","units_minimum":"1","units_maximum":"1","crse_offer_nbr":"1","term":"2093","crse_attr_list":"CSLI=N, ULR=UUSH"},"2094":{"crse_id":"000120","subject":"ASMT","catalog_nbr":"431","course_title_long":"US Histories","descrlong":"Alternative assessment of the U.S. Histories (HIST) University Learning Requirement.","units_minimum":"1","units_maximum":"1","crse_offer_nbr":"1","term":"2094","crse_attr_list":"CSLI=N, ULR=UUSH"},"2102":{"crse_id":"000120","subject":"ASMT","catalog_nbr":"431","course_title_long":"US Histories","descrlong":"Alternative assessment of the U.S. Histories (HIST) University Learning Requirement.","units_minimum":"1","units_maximum":"1","crse_offer_nbr":"1","term":"2102","crse_attr_list":"CSLI=N, ULR=UUSH"},"2103":{"crse_id":"000120","subject":"ASMT","catalog_nbr":"431","course_title_long":"US Histories","descrlong":"Alternative assessment of the U.S. Histories (HIST) University Learning Requirement.","units_minimum":"1","units_maximum":"1","crse_offer_nbr":"1","term":"2103","crse_attr_list":"CSLI=N, ULR=UUSH"},"2104":{"crse_id":"000120","subject":"ASMT","catalog_nbr":"431","course_title_long":"US Histories","descrlong":"Alternative assessment of the U.S. Histories (HIST) University Learning Requirement.","units_minimum":"1","units_maximum":"1","crse_offer_nbr":"1","term":"2104","crse_attr_list":"CSLI=N, ULR=UUSH"},"2112":{"crse_id":"000120","subject":"ASMT","catalog_nbr":"431","course_title_long":"US Histories","descrlong":"Alternative assessment of the U.S. Histories (HIST) University Learning Requirement.","units_minimum":"1","units_maximum":"1","crse_offer_nbr":"1","term":"2112","crse_attr_list":"CSLI=N, ULR=UUSH"},"2113":{"crse_id":"000120","subject":"ASMT","catalog_nbr":"431","course_title_long":"US Histories","descrlong":"Alternative assessment of the U.S. Histories (HIST) University Learning Requirement.","units_minimum":"1","units_maximum":"1","crse_offer_nbr":"1","term":"2113","crse_attr_list":"CSLI=N, ULR=UUSH"},"2114":{"crse_id":"000120","subject":"ASMT","catalog_nbr":"431","course_title_long":"US Histories","descrlong":"Alternative assessment of the U.S. Histories (HIST) University Learning Requirement.","units_minimum":"1","units_maximum":"1","crse_offer_nbr":"1","term":"2114","crse_attr_list":"CSLI=N, ULR=UUSH"},"2122":{"crse_id":"000120","subject":"ASMT","catalog_nbr":"431","course_title_long":"US Histories","descrlong":"Alternative assessment of the U.S. Histories (HIST) University Learning Requirement.","units_minimum":"1","units_maximum":"1","crse_offer_nbr":"1","term":"2122","crse_attr_list":"CSLI=N, ULR=UUSH"},"2123":{"crse_id":"000120","subject":"ASMT","catalog_nbr":"431","course_title_long":"US Histories","descrlong":"Alternative assessment of the U.S. Histories (HIST) University Learning Requirement.","units_minimum":"1","units_maximum":"1","crse_offer_nbr":"1","term":"2123","crse_attr_list":"CSLI=N, ULR=UUSH"},"2124":{"crse_id":"000120","subject":"ASMT","catalog_nbr":"431","course_title_long":"US Histories","descrlong":"Alternative assessment of the U.S. Histories (HIST) University Learning Requirement.","units_minimum":"1","units_maximum":"1","crse_offer_nbr":"1","term":"2124","crse_attr_list":"CSLI=N"},"2131":{"crse_id":"000120","subject":"ASMT","catalog_nbr":"431","course_title_long":"US Histories","descrlong":"Alternative assessment of the U.S. Histories (HIST) University Learning Requirement.","units_minimum":"1","units_maximum":"1","crse_offer_nbr":"1","term":"2131","crse_attr_list":"CSLI=N"},"2132":{"crse_id":"000120","subject":"ASMT","catalog_nbr":"431","course_title_long":"US Histories","descrlong":"Alternative assessment of the U.S. Histories (HIST) University Learning Requirement.","units_minimum":"1","units_maximum":"1","crse_offer_nbr":"1","term":"2132","crse_attr_list":"CSLI=N"},"2133":{"crse_id":"000120","subject":"ASMT","catalog_nbr":"431","course_title_long":"US Histories","descrlong":"Alternative assessment of the U.S. Histories (HIST) University Learning Requirement.","units_minimum":"1","units_maximum":"1","crse_offer_nbr":"1","term":"2133","crse_attr_list":"CSLI=N"},"2134":{"crse_id":"000120","subject":"ASMT","catalog_nbr":"431","course_title_long":"US Histories","descrlong":"Alternative assessment of the U.S. Histories (HIST) University Learning Requirement.","units_minimum":"1","units_maximum":"1","crse_offer_nbr":"1","term":"2134","crse_attr_list":"CSLI=N"},"2141":{"crse_id":"000120","subject":"ASMT","catalog_nbr":"431","course_title_long":"US Histories","descrlong":"Alternative assessment of the U.S. Histories (HIST) University Learning Requirement.","units_minimum":"1","units_maximum":"1","crse_offer_nbr":"1","term":"2141","crse_attr_list":"CSLI=N"},"2142":{"crse_id":"000120","subject":"ASMT","catalog_nbr":"431","course_title_long":"US Histories","descrlong":"Alternative assessment of the U.S. Histories (HIST) University Learning Requirement.","units_minimum":"1","units_maximum":"1","crse_offer_nbr":"1","term":"2142","crse_attr_list":"CSLI=N"},"2143":{"crse_id":"000120","subject":"ASMT","catalog_nbr":"431","course_title_long":"US Histories","descrlong":"Alternative assessment of the U.S. Histories (HIST) University Learning Requirement.","units_minimum":"1","units_maximum":"1","crse_offer_nbr":"1","term":"2143","crse_attr_list":"CSLI=N"}}