{"2164":{"crse_id":"142","subject":"BIO","catalog_nbr":"341","course_title_long":"Evolution Bio & Pop Genetics","descrlong":"Overview and explanation of evolutionary processes, ranging from microevolutionary changes in allelic frequency due to mutation, genetic drift, gene flow and natural selection to macroevolutionary processes such as speciation, extinction and the evolution of biodiversity.\n\n(Prereq: BIO 210 and BIO 211)","units_minimum":"3","units_maximum":"3","crse_offer_nbr":"1","term":"2164"}}