{"2082":{"crse_id":"000475","subject":"CST","catalog_nbr":"221","course_title_long":"Scripting for Multimedia","descrlong":"Students learn Flash Action Scripting and apply solid programming techniques to create dynamic multimedia content. Students learn the fundamental concepts of Object Oriented Programming plus designing, coding, testing, debugging, and documenting of computer programs. Using Flash Action Scripting, students apply those concepts to create programs utilizing digital media, including images, animation, audio, video and text. This is a laboratory class using Windows or Macintosh computers. (Offered fall semester.)","units_minimum":"2","units_maximum":"4","crse_offer_nbr":"1","term":"2082","crse_attr_list":"CSLI=N"}}