{"2164":{"crse_id":"1206","subject":"ENVS","catalog_nbr":"660","course_title_long":"Adv Watershed Sci & Policy","descrlong":"Addresses current watershed environmental issues using advanced research methods and sound science. Considers issues from multiple perspectives, including legal, political, diverse stakeholders, and natural science.  Students present project results in both written and oral formats, utilizing innovative visualizations, as necessary, to communicate technical science to decision-makers or non-specialists. (Offered fall semester.)","units_minimum":"4","units_maximum":"4","crse_offer_nbr":"1","term":"2164"}}