{"2172":{"crse_id":"005408","subject":"HCOM","catalog_nbr":"410","course_title_long":"Public Relations Ethics and Practices","descrlong":"Students will study public relations models and theories, as well as practical public relations skills to better interact with myriad publics. Participants will explore multiple ethical frameworks and apply them to the numerous issues facing public relations professionals. \r\n\r\n(Prereq: GE Areas A1 and A2 and A3)","units_minimum":"4","units_maximum":"4","crse_offer_nbr":"1","term":"2172","crse_attr_list":"CSLI=N"}}