{"2164":{"crse_id":"1425","subject":"HCOM","catalog_nbr":"327","course_title_long":"Survey American Literature","descrlong":"Examines American literature through different historical periods, literary genres, and cultural movements. Develops ability to compare and contrast social, historical, and cultural experiences represented in literature. Students gain cross-cultural knowledge of American literary history, an introduction to literary theory, and further development of literary analysis skills. Offers built-in assessment in HCOM MLO 6 or the concentration in Literary and Film Studies. Meets the Single Subject in English Waiver Literary Histories, Theories, and Praxis Requirement. A literature course from GE Area C2 is highly recommended. (Offered every other year.)\n\n(Prereq: GE Area A1 and A2 and A3)","units_minimum":"4","units_maximum":"4","crse_offer_nbr":"1","term":"2164"}}