{"2164":{"crse_id":"1444","subject":"HCOM","catalog_nbr":"342","course_title_long":"Feminist Theories & Methods","descrlong":"Explores modes of analysis that engage the intersectionality of gender, sexuality, race/ethnicity, economic class, and (dis)ability. Readings and activities will ponder the ways that different feminist theoretical paradigms work to advance social justice. Offers built-in assessment in HCOM MLO 5 or the concentrations in Women's Studies or Comparative American Studies. (Offered every year.)\n\n(Prereq: GE Area A1 and A2 and A3)","units_minimum":"4","units_maximum":"4","crse_offer_nbr":"1","term":"2164"}}