{"2073":{"crse_id":"001657","subject":"HPWE","catalog_nbr":"469","course_title_long":"Sp Top Intern: Exercise Sci","descrlong":"Students complete fieldwork in an agency/facility approved by the Exercise Science faculty.  Approval is  based on the opportunities available for students to work on issues of importance in the exercise science areas, and the agency's ability to provide mentoring and organizational support for the student intern.  Check with the HPWE Department for further information. (Taken after completion of required courses in concentration.)","units_minimum":"4","units_maximum":"4","crse_offer_nbr":"1","term":"2073","crse_attr_list":"CSLI=N"}}