{"2024":{"crse_id":"001762","subject":"HWI","catalog_nbr":"280L","course_title_long":"Scuba Diving Lab","descrlong":"","units_minimum":"1","units_maximum":"1","crse_offer_nbr":"1","term":"2024","crse_attr_list":"CSLI=N, ULR=UVBA"},"2031":{"crse_id":"001762","subject":"HWI","catalog_nbr":"280L","course_title_long":"Scuba Diving Lab","descrlong":"","units_minimum":"1","units_maximum":"1","crse_offer_nbr":"1","term":"2031","crse_attr_list":"CSLI=N, ULR=UVBA"},"2032":{"crse_id":"001762","subject":"HWI","catalog_nbr":"280L","course_title_long":"Scuba Diving Lab","descrlong":"","units_minimum":"1","units_maximum":"1","crse_offer_nbr":"1","term":"2032","crse_attr_list":"CSLI=N, ULR=UVBA"},"2033":{"crse_id":"001762","subject":"HWI","catalog_nbr":"280L","course_title_long":"Scuba Diving Lab","descrlong":"","units_minimum":"1","units_maximum":"1","crse_offer_nbr":"1","term":"2033","crse_attr_list":"CSLI=N, ULR=UVBA"},"2034":{"crse_id":"001762","subject":"HWI","catalog_nbr":"280L","course_title_long":"Scuba Diving Lab","descrlong":"","units_minimum":"2","units_maximum":"2","crse_offer_nbr":"1","term":"2034","crse_attr_list":"CSLI=N, ULR=UVBA"},"2041":{"crse_id":"001762","subject":"HWI","catalog_nbr":"280L","course_title_long":"Scuba Diving Lab","descrlong":"","units_minimum":"2","units_maximum":"2","crse_offer_nbr":"1","term":"2041","crse_attr_list":"CSLI=N, ULR=UVBA"},"2042":{"crse_id":"001762","subject":"HWI","catalog_nbr":"280L","course_title_long":"Scuba Diving Lab","descrlong":"","units_minimum":"2","units_maximum":"2","crse_offer_nbr":"1","term":"2042","crse_attr_list":"CSLI=N, ULR=UVBA"},"2043":{"crse_id":"001762","subject":"HWI","catalog_nbr":"280L","course_title_long":"Scuba Diving Lab","descrlong":"","units_minimum":"2","units_maximum":"2","crse_offer_nbr":"1","term":"2043","crse_attr_list":"CSLI=N, ULR=UVBA"}}