{"2174":{"crse_id":"001909","subject":"ITAL","catalog_nbr":"102","course_title_long":"Beginning Italian II","descrlong":"Continues the study of the Italian language emphasizing the mastery of oral communication and use of the written language. Includes the fundamentals of grammar, speaking, reading, and pronunciation.  Requires active participation in instructor-coordinated multimedia and online activities as a mandatory component. (Offered spring semester.)  \r\n\r\n(Prereq: ITAL 101)","units_minimum":"4","units_maximum":"4","crse_offer_nbr":"1","term":"2174","crse_attr_list":"CSLI=N, GE=C3"}}