{"2164":{"crse_id":"2176","subject":"MAE","catalog_nbr":"600","course_title_long":"Seminar in Educational Psychology","descrlong":"The cultural and political contexts of learning are examined, especially with regard to providing effective educational experiences for diverse populations. Participants are provided with an overview of Ed Psych theories which allows them to utilize various research methods to contrast differing perspectives and ways of knowing. In addition to building library research skills, students actively contribute to change or the existing knowledge base.\n\n(Restricted to MAE Majors)","units_minimum":"3","units_maximum":"3","crse_offer_nbr":"1","term":"2164"}}