{"2193":{"crse_id":"004705","subject":"NURS","catalog_nbr":"430","course_title_long":"Research and Evidence-Based Practice for The Nursing Profession","descrlong":"Emphasis on application of research methodology to utilize evidence by developing critical reasoning skills needed to comprehend formal scientific reports. Development of critical judgement skills to critique/appraise current/relevant healthcare research to effectively analyze and evaluate multiple perspectives for making sound clinical decisions. Communicate evidence effectively/ethically in written reports and oral presentations for nursing discipline. (Department of Nursing consent required.)\r\n\r\n[(Prereq:  NURS 300 and NURS 301 and NURS 302 and NURS 321) and (Coreq: NURS 306 and NURS 310 and NURS 350)]","units_minimum":"3","units_maximum":"3","crse_offer_nbr":"1","term":"2193","crse_attr_list":"CSLI=N"}}