{"2164":{"crse_id":"4004","subject":"PHYS","catalog_nbr":"330","course_title_long":"Robotics for Ecological Research","descrlong":"Through a series of hands-on project modules, students develop practical skills in electronics, microcontroller programming, and robotics sufficient to design and build a simple, programmable robot, sensor/datalogger system, or other electronic device for collecting environmental measurements in terrestrial, freshwater, or marine ecosystems. Course fee may be required.\n\n[Prereq: MATH 150 and (PHYS 121 or PHYS 150 or PHYS 220 or CST 231)]","units_minimum":"4","units_maximum":"4","crse_offer_nbr":"1","term":"2164"}}